[{"timestamp":1629930093433,"files":[{"filename":"bundle.*****.esm.js","previous":131373,"size":131279,"diff":-94},{"filename":"polyfills.*****.esm.js","previous":2181,"size":2181,"diff":0},{"filename":"polyfills.27dd8.js","previous":2178,"size":2178,"diff":0},{"filename":"index.html","previous":785,"size":784,"diff":-1},{"filename":"sw-esm.js","previous":10677,"size":10674,"diff":-3},{"filename":"200.html","previous":791,"size":790,"diff":-1},{"filename":"bundle.985aa.css","previous":2742,"size":2742,"diff":0},{"filename":"bundle.4a587.js","previous":131384,"size":0,"diff":-131384},{"filename":"bundle.052e9.js","previous":0,"size":131304,"diff":131304}]},{"timestamp":1626451135307,"files":[{"filename":"bundle.*****.esm.js","previous":131350,"size":131373,"diff":23},{"filename":"polyfills.*****.esm.js","previous":2181,"size":2181,"diff":0},{"filename":"polyfills.27dd8.js","previous":2178,"size":2178,"diff":0},{"filename":"index.html","previous":783,"size":785,"diff":2},{"filename":"sw-esm.js","previous":10674,"size":10677,"diff":3},{"filename":"200.html","previous":789,"size":791,"diff":2},{"filename":"bundle.36fea.css","previous":2742,"size":0,"diff":-2742},{"filename":"bundle.f45c7.js","previous":131369,"size":0,"diff":-131369},{"filename":"bundle.985aa.css","previous":0,"size":2742,"diff":2742},{"filename":"bundle.4a587.js","previous":0,"size":131384,"diff":131384}]},{"timestamp":1625240744296,"files":[{"filename":"bundle.*****.esm.js","previous":131344,"size":131350,"diff":6},{"filename":"polyfills.*****.esm.js","previous":2181,"size":2181,"diff":0},{"filename":"polyfills.27dd8.js","previous":2178,"size":2178,"diff":0},{"filename":"index.html","previous":784,"size":783,"diff":-1},{"filename":"sw-esm.js","previous":10676,"size":10674,"diff":-2},{"filename":"200.html","previous":790,"size":789,"diff":-1},{"filename":"bundle.37d89.css","previous":2719,"size":0,"diff":-2719},{"filename":"bundle.5200d.js","previous":131362,"size":0,"diff":-131362},{"filename":"bundle.36fea.css","previous":0,"size":2742,"diff":2742},{"filename":"bundle.f45c7.js","previous":0,"size":131369,"diff":131369}]},{"timestamp":1625174625935,"files":[{"filename":"bundle.*****.esm.js","previous":131543,"size":131344,"diff":-199},{"filename":"polyfills.*****.esm.js","previous":2181,"size":2181,"diff":0},{"filename":"polyfills.27dd8.js","previous":2178,"size":2178,"diff":0},{"filename":"index.html","previous":762,"size":784,"diff":22},{"filename":"sw-esm.js","previous":10672,"size":10676,"diff":4},{"filename":"200.html","previous":768,"size":790,"diff":22},{"filename":"bundle.a8a28.css","previous":2691,"size":0,"diff":-2691},{"filename":"bundle.a612e.js","previous":131555,"size":0,"diff":-131555},{"filename":"bundle.37d89.css","previous":0,"size":2719,"diff":2719},{"filename":"bundle.5200d.js","previous":0,"size":131362,"diff":131362}]},{"timestamp":1625070415489,"files":[{"filename":"bundle.*****.esm.js","previous":131477,"size":131543,"diff":66},{"filename":"polyfills.*****.esm.js","previous":2181,"size":2181,"diff":0},{"filename":"polyfills.27dd8.js","previous":2178,"size":2178,"diff":0},{"filename":"index.html","previous":768,"size":762,"diff":-6},{"filename":"bundle.d2086.css","previous":2651,"size":0,"diff":-2651},{"filename":"sw-esm.js","previous":10673,"size":10672,"diff":-1},{"filename":"bundle.9056c.js","previous":131498,"size":0,"diff":-131498},{"filename":"200.html","previous":773,"size":768,"diff":-5},{"filename":"bundle.a8a28.css","previous":0,"size":2691,"diff":2691},{"filename":"bundle.a612e.js","previous":0,"size":131555,"diff":131555}]},{"timestamp":1625060567105,"files":[{"filename":"bundle.*****.esm.js","previous":124088,"size":131477,"diff":7389},{"filename":"polyfills.*****.esm.js","previous":2181,"size":2181,"diff":0},{"filename":"polyfills.27dd8.js","previous":2178,"size":2178,"diff":0},{"filename":"index.html","previous":749,"size":768,"diff":19},{"filename":"bundle.c6322.css","previous":2154,"size":0,"diff":-2154},{"filename":"bundle.3c2d5.js","previous":124137,"size":0,"diff":-124137},{"filename":"bundle.d2086.css","previous":0,"size":2651,"diff":2651},{"filename":"sw-esm.js","previous":0,"size":10673,"diff":10673},{"filename":"bundle.9056c.js","previous":0,"size":131498,"diff":131498},{"filename":"200.html","previous":0,"size":773,"diff":773}]},{"timestamp":1623450396430,"files":[{"filename":"bundle.*****.esm.js","previous":124089,"size":124088,"diff":-1},{"filename":"polyfills.*****.esm.js","previous":2181,"size":2181,"diff":0},{"filename":"polyfills.27dd8.js","previous":2178,"size":2178,"diff":0},{"filename":"index.html","previous":751,"size":749,"diff":-2},{"filename":"bundle.c32d2.css","previous":2147,"size":0,"diff":-2147},{"filename":"bundle.f4614.js","previous":124137,"size":0,"diff":-124137},{"filename":"bundle.c6322.css","previous":0,"size":2154,"diff":2154},{"filename":"bundle.3c2d5.js","previous":0,"size":124137,"diff":124137}]},{"timestamp":1623449215570,"files":[{"filename":"bundle.*****.esm.js","previous":124055,"size":124089,"diff":34},{"filename":"polyfills.*****.esm.js","previous":2181,"size":2181,"diff":0},{"filename":"polyfills.27dd8.js","previous":2178,"size":2178,"diff":0},{"filename":"index.html","previous":743,"size":751,"diff":8},{"filename":"bundle.28373.css","previous":2559,"size":0,"diff":-2559},{"filename":"bundle.08bbc.js","previous":124099,"size":0,"diff":-124099},{"filename":"bundle.c32d2.css","previous":0,"size":2147,"diff":2147},{"filename":"bundle.f4614.js","previous":0,"size":124137,"diff":124137}]},{"timestamp":1623444344837,"files":[{"filename":"bundle.*****.esm.js","previous":124051,"size":124055,"diff":4},{"filename":"polyfills.*****.esm.js","previous":2181,"size":2181,"diff":0},{"filename":"polyfills.27dd8.js","previous":2178,"size":2178,"diff":0},{"filename":"index.html","previous":742,"size":743,"diff":1},{"filename":"bundle.28373.css","previous":2559,"size":2559,"diff":0},{"filename":"bundle.713ea.js","previous":124095,"size":0,"diff":-124095},{"filename":"bundle.08bbc.js","previous":0,"size":124099,"diff":124099}]},{"timestamp":1623444058525,"files":[{"filename":"bundle.*****.esm.js","previous":124034,"size":124051,"diff":17},{"filename":"polyfills.*****.esm.js","previous":2181,"size":2181,"diff":0},{"filename":"polyfills.27dd8.js","previous":2178,"size":2178,"diff":0},{"filename":"index.html","previous":743,"size":742,"diff":-1},{"filename":"bundle.28373.css","previous":2559,"size":2559,"diff":0},{"filename":"bundle.0ac39.js","previous":124079,"size":0,"diff":-124079},{"filename":"bundle.713ea.js","previous":0,"size":124095,"diff":124095}]},{"timestamp":1623443586007,"files":[{"filename":"bundle.*****.esm.js","previous":123973,"size":124034,"diff":61},{"filename":"polyfills.*****.esm.js","previous":2181,"size":2181,"diff":0},{"filename":"polyfills.27dd8.js","previous":2178,"size":2178,"diff":0},{"filename":"index.html","previous":743,"size":743,"diff":0},{"filename":"bundle.28373.css","previous":2559,"size":2559,"diff":0},{"filename":"bundle.a0035.js","previous":124017,"size":0,"diff":-124017},{"filename":"bundle.0ac39.js","previous":0,"size":124079,"diff":124079}]},{"timestamp":1623443196508,"files":[{"filename":"bundle.*****.esm.js","previous":123952,"size":123973,"diff":21},{"filename":"polyfills.*****.esm.js","previous":2181,"size":2181,"diff":0},{"filename":"polyfills.27dd8.js","previous":2178,"size":2178,"diff":0},{"filename":"index.html","previous":743,"size":743,"diff":0},{"filename":"bundle.28373.css","previous":2559,"size":2559,"diff":0},{"filename":"bundle.bf4b2.js","previous":123997,"size":0,"diff":-123997},{"filename":"bundle.a0035.js","previous":0,"size":124017,"diff":124017}]},{"timestamp":1623442941631,"files":[{"filename":"bundle.*****.esm.js","previous":123968,"size":123952,"diff":-16},{"filename":"polyfills.*****.esm.js","previous":2181,"size":2181,"diff":0},{"filename":"polyfills.27dd8.js","previous":2178,"size":2178,"diff":0},{"filename":"index.html","previous":744,"size":743,"diff":-1},{"filename":"bundle.28373.css","previous":2559,"size":2559,"diff":0},{"filename":"bundle.94886.js","previous":124012,"size":0,"diff":-124012},{"filename":"bundle.bf4b2.js","previous":0,"size":123997,"diff":123997}]},{"timestamp":1623442546461,"files":[{"filename":"bundle.*****.esm.js","previous":124011,"size":123968,"diff":-43},{"filename":"polyfills.*****.esm.js","previous":2181,"size":2181,"diff":0},{"filename":"sw-esm.js","previous":10675,"size":0,"diff":-10675},{"filename":"polyfills.27dd8.js","previous":2178,"size":2178,"diff":0},{"filename":"index.html","previous":742,"size":744,"diff":2},{"filename":"200.html","previous":742,"size":0,"diff":-742},{"filename":"bundle.28373.css","previous":2559,"size":2559,"diff":0},{"filename":"bundle.f3b03.js","previous":124052,"size":0,"diff":-124052},{"filename":"bundle.94886.js","previous":0,"size":124012,"diff":124012}]},{"timestamp":1623442313468,"files":[{"filename":"bundle.*****.esm.js","previous":124045,"size":124011,"diff":-34},{"filename":"polyfills.*****.esm.js","previous":2181,"size":2181,"diff":0},{"filename":"sw-esm.js","previous":10675,"size":10675,"diff":0},{"filename":"polyfills.27dd8.js","previous":2178,"size":2178,"diff":0},{"filename":"index.html","previous":801,"size":742,"diff":-59},{"filename":"200.html","previous":807,"size":742,"diff":-65},{"filename":"bundle.28373.css","previous":2559,"size":2559,"diff":0},{"filename":"bundle.a5895.js","previous":124091,"size":0,"diff":-124091},{"filename":"bundle.f3b03.js","previous":0,"size":124052,"diff":124052}]},{"timestamp":1623442073032,"files":[{"filename":"bundle.*****.esm.js","previous":124058,"size":124045,"diff":-13},{"filename":"polyfills.*****.esm.js","previous":2181,"size":2181,"diff":0},{"filename":"sw-esm.js","previous":10676,"size":10675,"diff":-1},{"filename":"polyfills.27dd8.js","previous":2178,"size":2178,"diff":0},{"filename":"index.html","previous":802,"size":801,"diff":-1},{"filename":"200.html","previous":806,"size":807,"diff":1},{"filename":"bundle.28373.css","previous":2559,"size":2559,"diff":0},{"filename":"bundle.2b693.js","previous":124105,"size":0,"diff":-124105},{"filename":"bundle.a5895.js","previous":0,"size":124091,"diff":124091}]},{"timestamp":1623440087233,"files":[{"filename":"bundle.*****.esm.js","previous":124029,"size":124058,"diff":29},{"filename":"polyfills.*****.esm.js","previous":2181,"size":2181,"diff":0},{"filename":"sw-esm.js","previous":10677,"size":10676,"diff":-1},{"filename":"polyfills.27dd8.js","previous":2178,"size":2178,"diff":0},{"filename":"index.html","previous":1549,"size":802,"diff":-747},{"filename":"200.html","previous":806,"size":806,"diff":0},{"filename":"bundle.28373.css","previous":2559,"size":2559,"diff":0},{"filename":"bundle.a711a.js","previous":124073,"size":0,"diff":-124073},{"filename":"bundle.2b693.js","previous":0,"size":124105,"diff":124105}]},{"timestamp":1623439469312,"files":[{"filename":"bundle.*****.esm.js","previous":124028,"size":124029,"diff":1},{"filename":"polyfills.*****.esm.js","previous":2181,"size":2181,"diff":0},{"filename":"sw-esm.js","previous":10673,"size":10677,"diff":4},{"filename":"polyfills.27dd8.js","previous":2178,"size":2178,"diff":0},{"filename":"index.html","previous":1549,"size":1549,"diff":0},{"filename":"200.html","previous":806,"size":806,"diff":0},{"filename":"bundle.ea0b7.css","previous":2559,"size":0,"diff":-2559},{"filename":"bundle.3899f.js","previous":124074,"size":0,"diff":-124074},{"filename":"bundle.28373.css","previous":0,"size":2559,"diff":2559},{"filename":"bundle.a711a.js","previous":0,"size":124073,"diff":124073}]},{"timestamp":1623439310841,"files":[{"filename":"bundle.*****.esm.js","previous":124029,"size":124028,"diff":-1},{"filename":"polyfills.*****.esm.js","previous":2181,"size":2181,"diff":0},{"filename":"sw-esm.js","previous":10678,"size":10673,"diff":-5},{"filename":"polyfills.27dd8.js","previous":2178,"size":2178,"diff":0},{"filename":"index.html","previous":1547,"size":1549,"diff":2},{"filename":"200.html","previous":806,"size":806,"diff":0},{"filename":"bundle.e91b6.css","previous":1285,"size":0,"diff":-1285},{"filename":"bundle.5c9a8.js","previous":124073,"size":0,"diff":-124073},{"filename":"bundle.ea0b7.css","previous":0,"size":2559,"diff":2559},{"filename":"bundle.3899f.js","previous":0,"size":124074,"diff":124074}]},{"timestamp":1623439203076,"files":[{"filename":"bundle.*****.esm.js","previous":124029,"size":124029,"diff":0},{"filename":"polyfills.*****.esm.js","previous":2181,"size":2181,"diff":0},{"filename":"sw-esm.js","previous":10675,"size":10678,"diff":3},{"filename":"polyfills.27dd8.js","previous":2178,"size":2178,"diff":0},{"filename":"index.html","previous":403,"size":1547,"diff":1144},{"filename":"200.html","previous":403,"size":806,"diff":403},{"filename":"bundle.9273e.css","previous":2621,"size":0,"diff":-2621},{"filename":"bundle.5990a.js","previous":124073,"size":0,"diff":-124073},{"filename":"bundle.e91b6.css","previous":0,"size":1285,"diff":1285},{"filename":"bundle.5c9a8.js","previous":0,"size":124073,"diff":124073}]},{"timestamp":1623438913200,"files":[{"filename":"bundle.866c4.css","previous":1736,"size":0,"diff":-1736},{"filename":"bundle.*****.esm.js","previous":5731,"size":124029,"diff":118298},{"filename":"polyfills.*****.esm.js","previous":2181,"size":2181,"diff":0},{"filename":"sw-esm.js","previous":10676,"size":10675,"diff":-1},{"filename":"polyfills.27dd8.js","previous":2178,"size":2178,"diff":0},{"filename":"index.html","previous":878,"size":403,"diff":-475},{"filename":"200.html","previous":727,"size":403,"diff":-324},{"filename":"bundle.01014.js","previous":5369,"size":0,"diff":-5369},{"filename":"bundle.9273e.css","previous":0,"size":2621,"diff":2621},{"filename":"bundle.5990a.js","previous":0,"size":124073,"diff":124073}]},{"timestamp":1623233643563,"files":[{"filename":"bundle.866c4.css","previous":1736,"size":1736,"diff":0},{"filename":"bundle.*****.esm.js","previous":5759,"size":5731,"diff":-28},{"filename":"polyfills.*****.esm.js","previous":2181,"size":2181,"diff":0},{"filename":"sw-esm.js","previous":10674,"size":10676,"diff":2},{"filename":"bundle.6a149.js","previous":5395,"size":0,"diff":-5395},{"filename":"polyfills.27dd8.js","previous":2178,"size":2178,"diff":0},{"filename":"index.html","previous":722,"size":878,"diff":156},{"filename":"200.html","previous":728,"size":727,"diff":-1},{"filename":"bundle.01014.js","previous":0,"size":5369,"diff":5369}]},{"timestamp":1623232255555,"files":[{"filename":"ssr-build/ssr-bundle.866c4.css","previous":1800,"size":0,"diff":-1800},{"filename":"ssr-build/ssr-bundle.js","previous":1612,"size":0,"diff":-1612},{"filename":"bundle.866c4.css","previous":0,"size":1736,"diff":1736},{"filename":"bundle.*****.esm.js","previous":0,"size":5759,"diff":5759},{"filename":"polyfills.*****.esm.js","previous":0,"size":2181,"diff":2181},{"filename":"sw-esm.js","previous":0,"size":10674,"diff":10674},{"filename":"bundle.6a149.js","previous":0,"size":5395,"diff":5395},{"filename":"polyfills.27dd8.js","previous":0,"size":2178,"diff":2178},{"filename":"index.html","previous":0,"size":722,"diff":722},{"filename":"200.html","previous":0,"size":728,"diff":728}]}]
